pyRXPU.cpython-310-x86_64-linux-gnu.so
pyRXP-3.0.1.dist-info/METADATA
pyRXP-3.0.1.dist-info/LICENSE.txt
pyRXP-3.0.1.dist-info/WHEEL
pyRXP-3.0.1.dist-info/RECORD
pyRXP-3.0.1.dist-info/top_level.txt
